[
    {
        "text": "河童とみくる",
        "TL key": "河童とみくる",
        "byte_length": "0x0D"
    },
    {
        "text": "処女",
        "TL key": "処女",
        "byte_length": "0x05"
    },
    {
        "text": "非処女",
        "TL key": "非処女",
        "byte_length": "0x07"
    },
    {
        "text": "河童とみくる",
        "TL key": "河童とみくる",
        "byte_length": "0x0E"
    },
    {
        "text": "みくる",
        "TL key": "みくる",
        "byte_length": "0x07"
    },
    {
        "text": "「くぅ……もう観念するのですっ！」",
        "TL key": "「くぅ……もう観念するのですっ！」",
        "byte_length": "0x23"
    },
    {
        "text": "図らずも河童に負けたみくるだが、威勢だけは衰えていない。",
        "TL key": "図らずも河童に負けたみくるだが、威勢だけは衰えていない。",
        "byte_length": "0x39"
    },
    {
        "text": "「うう……放しなさい、でないと痛い目を見ますよっ！」",
        "TL key": "「うう……放しなさい、でないと痛い目を見ますよっ！」",
        "byte_length": "0x35"
    },
    {
        "text": "――などと叫ぶみくるだが、河童に拘束されて動けないでいる。",
        "TL key": "――などと叫ぶみくるだが、河童に拘束されて動けないでいる。",
        "byte_length": "0x3B"
    },
    {
        "text": "体力も霊力も果てた今、河童の拘束から逃れることは困難だ。",
        "TL key": "体力も霊力も果てた今、河童の拘束から逃れることは困難だ。",
        "byte_length": "0x39"
    },
    {
        "text": "「なんとか言うのですっ！」",
        "TL key": "「なんとか言うのですっ！」",
        "byte_length": "0x1B"
    },
    {
        "text": "水辺で拘束されてしまったみくるは、怯えの色を隠せない。",
        "TL key": "水辺で拘束されてしまったみくるは、怯えの色を隠せない。",
        "byte_length": "0x37"
    },
    {
        "text": "そこは河童にとって有利な場所だからだ。",
        "TL key": "そこは河童にとって有利な場所だからだ。",
        "byte_length": "0x27"
    },
    {
        "text": "やがて背後に立った河童はみくるの尻に何かを当ててきた。",
        "TL key": "やがて背後に立った河童はみくるの尻に何かを当ててきた。",
        "byte_length": "0x37"
    },
    {
        "text": "「きゃっ、な、何をしているのですかっ」",
        "TL key": "「きゃっ、な、何をしているのですかっ」",
        "byte_length": "0x27"
    },
    {
        "text": "河童の両手はみくるの両手を押さえつけているので、思い当たるものはひとつしかない。",
        "TL key": "河童の両手はみくるの両手を押さえつけているので、思い当たるものはひとつしかない。",
        "byte_length": "0x51"
    },
    {
        "text": "堅く反り返ったそれはぬるぬるとしていて、みくるの尻穴周りを擽ってきた。",
        "TL key": "堅く反り返ったそれはぬるぬるとしていて、みくるの尻穴周りを擽ってきた。",
        "byte_length": "0x47"
    },
    {
        "text": "「あっ、嫌っ、気持ち悪いっ……」",
        "TL key": "「あっ、嫌っ、気持ち悪いっ……」",
        "byte_length": "0x21"
    },
    {
        "text": "菊門の周りをほぐすように突いてくるのが不気味だ。",
        "TL key": "菊門の周りをほぐすように突いてくるのが不気味だ。",
        "byte_length": "0x31"
    },
    {
        "text": "（このままだとミクは犯されてしまうのです……）",
        "TL key": "（このままだとミクは犯されてしまうのです……）",
        "byte_length": "0x2F"
    },
    {
        "text": "河童の行為に不快感を露わにするみくるだが、抵抗する力は残っていない。",
        "TL key": "河童の行為に不快感を露わにするみくるだが、抵抗する力は残っていない。",
        "byte_length": "0x45"
    },
    {
        "text": "「もうっ、放すのですっ！」",
        "TL key": "「もうっ、放すのですっ！」",
        "byte_length": "0x1B"
    },
    {
        "text": "強めの口調で河童に話しかけるが、反応はない。",
        "TL key": "強めの口調で河童に話しかけるが、反応はない。",
        "byte_length": "0x2D"
    },
    {
        "text": "むしろみくるを掴んだ手に力がこもり、放すまいとしてくる。",
        "TL key": "むしろみくるを掴んだ手に力がこもり、放すまいとしてくる。",
        "byte_length": "0x39"
    },
    {
        "text": "「離してくれたら、あとでキュウリを上げますからっ」",
        "TL key": "「離してくれたら、あとでキュウリを上げますからっ」",
        "byte_length": "0x33"
    },
    {
        "text": "キュウリにも反応しない河童は会陰や菊門周りを撫でてくる。",
        "TL key": "キュウリにも反応しない河童は会陰や菊門周りを撫でてくる。",
        "byte_length": "0x39"
    },
    {
        "text": "知性の低い河童に交渉は不可能ということだろう。",
        "TL key": "知性の低い河童に交渉は不可能ということだろう。",
        "byte_length": "0x2F"
    },
    {
        "text": "（このままじゃ……）",
        "TL key": "（このままじゃ……）",
        "byte_length": "0x15"
    },
    {
        "text": "怖れと不安感でみくるの顔が青ざめる。",
        "TL key": "怖れと不安感でみくるの顔が青ざめる。",
        "byte_length": "0x25"
    },
    {
        "text": "しかし、河童は秘裂に興味はないらしく、菊門周りを愛撫してくるだけだ。",
        "TL key": "しかし、河童は秘裂に興味はないらしく、菊門周りを愛撫してくるだけだ。",
        "byte_length": "0x45"
    },
    {
        "text": "そういえば――。",
        "TL key": "そういえば――。",
        "byte_length": "0x11"
    },
    {
        "text": "（河童といえば尻小玉を抜くと言う伝承が……）",
        "TL key": "（河童といえば尻小玉を抜くと言う伝承が……）",
        "byte_length": "0x2D"
    },
    {
        "text": "言葉に出来ない不快感の中、河童の伝承を思い出したみくる。",
        "TL key": "言葉に出来ない不快感の中、河童の伝承を思い出したみくる。",
        "byte_length": "0x39"
    },
    {
        "text": "（尻小玉を抜く……）",
        "TL key": "（尻小玉を抜く……）",
        "byte_length": "0x15"
    },
    {
        "text": "伝承通りなら、尻から魂を抜かれてしまう――。",
        "TL key": "伝承通りなら、尻から魂を抜かれてしまう――。",
        "byte_length": "0x2D"
    },
    {
        "text": "しかし、実際の河童は女性を取り殺すことはない。",
        "TL key": "しかし、実際の河童は女性を取り殺すことはない。",
        "byte_length": "0x2F"
    },
    {
        "text": "肛門に挿入して苗床にすることをみくるは知っていた。",
        "TL key": "肛門に挿入して苗床にすることをみくるは知っていた。",
        "byte_length": "0x33"
    },
    {
        "text": "「嫌っ、放してっ、気持ち悪いのですっ」",
        "TL key": "「嫌っ、放してっ、気持ち悪いのですっ」",
        "byte_length": "0x27"
    },
    {
        "text": "掴まれた手を振り解こうとするが、びくともしない。",
        "TL key": "掴まれた手を振り解こうとするが、びくともしない。",
        "byte_length": "0x31"
    },
    {
        "text": "河童は足でみくるの立ち位置をずらし、腕を引っ張って前屈みにさせる。",
        "TL key": "河童は足でみくるの立ち位置をずらし、腕を引っ張って前屈みにさせる。",
        "byte_length": "0x43"
    },
    {
        "text": "「はっ、放してっ、放しなさいっ！」",
        "TL key": "「はっ、放してっ、放しなさいっ！」",
        "byte_length": "0x23"
    },
    {
        "text": "藻掻くみくるの菊門に、河童の逸物が当てられた。",
        "TL key": "藻掻くみくるの菊門に、河童の逸物が当てられた。",
        "byte_length": "0x2F"
    },
    {
        "text": "「お尻はいやですっ、気持ち悪いっ……」",
        "TL key": "「お尻はいやですっ、気持ち悪いっ……」",
        "byte_length": "0x27"
    },
    {
        "text": "河童のぬめりがある手はみくるをしっかりと掴んでいて、藻掻いても怪力で押さえつけられるだけだ。",
        "TL key": "河童のぬめりがある手はみくるをしっかりと掴んでいて、藻掻いても怪力で押さえつけられるだけだ。",
        "byte_length": "0x5D"
    },
    {
        "text": "これからその肉棒で犯すのだとでも言うように、じっくりと擦り付け始めていた。",
        "TL key": "これからその肉棒で犯すのだとでも言うように、じっくりと擦り付け始めていた。",
        "byte_length": "0x4B"
    },
    {
        "text": "「んんぅっ……！　いやっ……！　ダメっ……んんっ………離してぇ……！」",
        "TL key": "「んんぅっ……！　いやっ……！　ダメっ……んんっ………離してぇ……！」",
        "byte_length": "0x47"
    },
    {
        "text": "みくるは違和感と不快感に喘ぐ。",
        "TL key": "みくるは違和感と不快感に喘ぐ。",
        "byte_length": "0x1F"
    },
    {
        "text": "河童の逸物は雁首が高く、ぞろりぞろりと撫でてくる。",
        "TL key": "河童の逸物は雁首が高く、ぞろりぞろりと撫でてくる。",
        "byte_length": "0x33"
    },
    {
        "text": "「ぅんっ！　んんっ……んくぅっ……！」",
        "TL key": "「ぅんっ！　んんっ……んくぅっ……！」",
        "byte_length": "0x27"
    },
    {
        "text": "河童の逸物は、みくるからは見えないが相当大きいようだ。",
        "TL key": "河童の逸物は、みくるからは見えないが相当大きいようだ。",
        "byte_length": "0x37"
    },
    {
        "text": "じわじわとした感覚は、やがて痺れるような感覚に変わってゆく。",
        "TL key": "じわじわとした感覚は、やがて痺れるような感覚に変わってゆく。",
        "byte_length": "0x3D"
    },
    {
        "text": "「んんっ、あふっ、違和感が……いや、なのに……」",
        "TL key": "「んんっ、あふっ、違和感が……いや、なのに……」",
        "byte_length": "0x31"
    },
    {
        "text": "（妖怪にこんなことをされて、感じるわけないのです）",
        "TL key": "（妖怪にこんなことをされて、感じるわけないのです）",
        "byte_length": "0x33"
    },
    {
        "text": "かぶりを振って否定するみくるだが、閉じ合わさった秘裂がじっとりと濡れてきていることに気付いた。",
        "TL key": "かぶりを振って否定するみくるだが、閉じ合わさった秘裂がじっとりと濡れてきていることに気付いた。",
        "byte_length": "0x5F"
    },
    {
        "text": "（これはちがうのです、妖怪なんかに……）",
        "TL key": "（これはちがうのです、妖怪なんかに……）",
        "byte_length": "0x29"
    },
    {
        "text": "何度もかぶりを振って追い払おうとするが、異物に快感を覚え始めていた。",
        "TL key": "何度もかぶりを振って追い払おうとするが、異物に快感を覚え始めていた。",
        "byte_length": "0x45"
    },
    {
        "text": "そして力が抜けてきていることから頃合いだと判断したのか、{獰猛/どうもう}な形をした肉棒を尻穴へと押し当てる。",
        "TL key": "そして力が抜けてきていることから頃合いだと判断したのか、{獰猛/どうもう}な形をした肉棒を尻穴へと押し当てる。",
        "byte_length": "0x6C"
    },
    {
        "text": "「そこはっ、ダメですっ、いやあっ」",
        "TL key": "「そこはっ、ダメですっ、いやあっ」",
        "byte_length": "0x23"
    },
    {
        "text": "腰を左右に振って菊門への侵入を拒むみくる。",
        "TL key": "腰を左右に振って菊門への侵入を拒むみくる。",
        "byte_length": "0x2B"
    },
    {
        "text": "しかし、河童は的確に菊門へ亀頭を擦りつけてきた。",
        "TL key": "しかし、河童は的確に菊門へ亀頭を擦りつけてきた。",
        "byte_length": "0x31"
    },
    {
        "text": "河童の体液でヌルヌルとしたそれは、じわじわと菊門を押し広げてくる。",
        "TL key": "河童の体液でヌルヌルとしたそれは、じわじわと菊門を押し広げてくる。",
        "byte_length": "0x43"
    },
    {
        "text": "「つうっ……痛いっ、んんっ、んんーっ」",
        "TL key": "「つうっ……痛いっ、んんっ、んんーっ」",
        "byte_length": "0x27"
    },
    {
        "text": "剛直の侵入を拒むように括約筋を締め上げる。",
        "TL key": "剛直の侵入を拒むように括約筋を締め上げる。",
        "byte_length": "0x2B"
    },
    {
        "text": "「ひぐっ……！　んんっ、かはっ……！　くはぁっ……！」",
        "TL key": "「ひぐっ……！　んんっ、かはっ……！　くはぁっ……！」",
        "byte_length": "0x37"
    },
    {
        "text": "河童の逞しい肉棒を挿入され、大きく息を吐いた。",
        "TL key": "河童の逞しい肉棒を挿入され、大きく息を吐いた。",
        "byte_length": "0x2F"
    },
    {
        "text": "「んぐっ！　ひっ……あっ、ああっ！」",
        "TL key": "「んぐっ！　ひっ……あっ、ああっ！」",
        "byte_length": "0x25"
    },
    {
        "text": "尻穴への圧迫感にみくるは全身をこわばらせた。",
        "TL key": "尻穴への圧迫感にみくるは全身をこわばらせた。",
        "byte_length": "0x2D"
    },
    {
        "text": "「あぁ、ああ、はぁっ、あっ、くあぁっ……」",
        "TL key": "「あぁ、ああ、はぁっ、あっ、くあぁっ……」",
        "byte_length": "0x2B"
    },
    {
        "text": "くちゅくちゅと粘り気のある水音を立てて、河童の剛直がみくるの菊門を潜ってゆく。",
        "TL key": "くちゅくちゅと粘り気のある水音を立てて、河童の剛直がみくるの菊門を潜ってゆく。",
        "byte_length": "0x4F"
    },
    {
        "text": "「んんっ、んはぁっ、苦しいっ、いやぁ……ぬ、抜いて……お願い……んんっ……！」",
        "TL key": "「んんっ、んはぁっ、苦しいっ、いやぁ……ぬ、抜いて……お願い……んんっ……！」",
        "byte_length": "0x4F"
    },
    {
        "text": "亀頭が完全に菊門を貫いた辺りで、河童は腰の動きを止めた。",
        "TL key": "亀頭が完全に菊門を貫いた辺りで、河童は腰の動きを止めた。",
        "byte_length": "0x39"
    },
    {
        "text": "みくるの意志とは関係なく、ひくひくとわななく菊門を愉しんでいるようだ。",
        "TL key": "みくるの意志とは関係なく、ひくひくとわななく菊門を愉しんでいるようだ。",
        "byte_length": "0x47"
    },
    {
        "text": "（あ……だんだん慣れてきたみたいなのです……）",
        "TL key": "（あ……だんだん慣れてきたみたいなのです……）",
        "byte_length": "0x2F"
    },
    {
        "text": "異物挿入の不快感はあるものの、痛みは感じなくなっていた。",
        "TL key": "異物挿入の不快感はあるものの、痛みは感じなくなっていた。",
        "byte_length": "0x39"
    },
    {
        "text": "「んっ、んんっ、はぁっ、はふぅ……」",
        "TL key": "「んっ、んんっ、はぁっ、はふぅ……」",
        "byte_length": "0x25"
    },
    {
        "text": "力を抜くように呼吸をするみくる。",
        "TL key": "力を抜くように呼吸をするみくる。",
        "byte_length": "0x21"
    },
    {
        "text": "その様子を見た河童はゆっくりと解すように抽送を始めた。",
        "TL key": "その様子を見た河童はゆっくりと解すように抽送を始めた。",
        "byte_length": "0x37"
    },
    {
        "text": "「いやあっ、気持ち悪いっ、放してっ」",
        "TL key": "「いやあっ、気持ち悪いっ、放してっ」",
        "byte_length": "0x25"
    },
    {
        "text": "菊門を貫かれないように腰を左右に振って抵抗する。",
        "TL key": "菊門を貫かれないように腰を左右に振って抵抗する。",
        "byte_length": "0x31"
    },
    {
        "text": "しかし河童は剛直に手を添えずに菊門をこじ開けに掛かる。",
        "TL key": "しかし河童は剛直に手を添えずに菊門をこじ開けに掛かる。",
        "byte_length": "0x37"
    },
    {
        "text": "「んんっ……！　ぅんっ、んっ、んっ……んくぅっ……！」",
        "TL key": "「んんっ……！　ぅんっ、んっ、んっ……んくぅっ……！」",
        "byte_length": "0x37"
    },
    {
        "text": "ぬるりとした感触が菊門を潜ろうとしてきた。",
        "TL key": "ぬるりとした感触が菊門を潜ろうとしてきた。",
        "byte_length": "0x2B"
    },
    {
        "text": "「あぁっ……はぁっ、んっ……く……ぅっ……」",
        "TL key": "「あぁっ……はぁっ、んっ……く……ぅっ……」",
        "byte_length": "0x2D"
    },
    {
        "text": "なんとか押し返そうと力むみくる。",
        "TL key": "なんとか押し返そうと力むみくる。",
        "byte_length": "0x21"
    },
    {
        "text": "「あ、あ……はぁっ……く……」",
        "TL key": "「あ、あ……はぁっ……く……」",
        "byte_length": "0x1F"
    },
    {
        "text": "だが、抵抗も虚しく菊門の中に侵入を許してしまった。",
        "TL key": "だが、抵抗も虚しく菊門の中に侵入を許してしまった。",
        "byte_length": "0x33"
    },
    {
        "text": "「くぅううっ、あぁぁぁぁぁぁぁっ！」",
        "TL key": "「くぅううっ、あぁぁぁぁぁぁぁっ！」",
        "byte_length": "0x25"
    },
    {
        "text": "尻穴を深々と貫かれ、みくるはその圧迫感に悶絶する。",
        "TL key": "尻穴を深々と貫かれ、みくるはその圧迫感に悶絶する。",
        "byte_length": "0x33"
    },
    {
        "text": "「う……あ、あ、……やぁっ……」",
        "TL key": "「う……あ、あ、……やぁっ……」",
        "byte_length": "0x21"
    },
    {
        "text": "（お、お尻……お尻が……）",
        "TL key": "（お、お尻……お尻が……）",
        "byte_length": "0x1B"
    },
    {
        "text": "以前、他の妖怪に尻穴を弄ばれた記憶が蘇る。",
        "TL key": "以前、他の妖怪に尻穴を弄ばれた記憶が蘇る。",
        "byte_length": "0x2B"
    },
    {
        "text": "（うぅ……でも、ここは我慢のしどころなのです……）",
        "TL key": "（うぅ……でも、ここは我慢のしどころなのです……）",
        "byte_length": "0x33"
    },
    {
        "text": "（下手に抵抗するより、早く終わらないと……行為が終われば必ず放してくれるはずなのですから……）",
        "TL key": "（下手に抵抗するより、早く終わらないと……行為が終われば必ず放してくれるはずなのですから……）",
        "byte_length": "0x5F"
    },
    {
        "text": "そう決意したみくるは、河童が行為を終わらせるまで我慢することにした。",
        "TL key": "そう決意したみくるは、河童が行為を終わらせるまで我慢することにした。",
        "byte_length": "0x45"
    },
    {
        "text": "ゆっくり根元まで肉棒を押し込むと、河童はそのまま抽送を開始した。",
        "TL key": "ゆっくり根元まで肉棒を押し込むと、河童はそのまま抽送を開始した。",
        "byte_length": "0x41"
    },
    {
        "text": "「んんっ、んあっ、太いのがっ、やあっ、ごりごりしてる」",
        "TL key": "「んんっ、んあっ、太いのがっ、やあっ、ごりごりしてる」",
        "byte_length": "0x37"
    },
    {
        "text": "まずは手始めにとゆっくりみくるの尻穴を味わい始める河童。",
        "TL key": "まずは手始めにとゆっくりみくるの尻穴を味わい始める河童。",
        "byte_length": "0x39"
    },
    {
        "text": "「んっ、はぁっ、くぅっ……んんっ、ああっ……」",
        "TL key": "「んっ、はぁっ、くぅっ……んんっ、ああっ……」",
        "byte_length": "0x2F"
    },
    {
        "text": "腸内の締め付けを確かめるようにゆっくり腰を動かし始める河童。",
        "TL key": "腸内の締め付けを確かめるようにゆっくり腰を動かし始める河童。",
        "byte_length": "0x3D"
    },
    {
        "text": "「うあ、あっ、ん、んぐ、う、うあぁあ……」",
        "TL key": "「うあ、あっ、ん、んぐ、う、うあぁあ……」",
        "byte_length": "0x2B"
    },
    {
        "text": "腸壁を刺激しながら抽送を繰り返す肉棒に、無意識に身体へ力が入る。",
        "TL key": "腸壁を刺激しながら抽送を繰り返す肉棒に、無意識に身体へ力が入る。",
        "byte_length": "0x41"
    },
    {
        "text": "それに合わせて尻穴が窄み、挿入されている肉棒を激しく締め付けていく。",
        "TL key": "それに合わせて尻穴が窄み、挿入されている肉棒を激しく締め付けていく。",
        "byte_length": "0x45"
    },
    {
        "text": "「うあぁ……あっ、ん、んん……くぅ……ん、んあ、あああっ」",
        "TL key": "「うあぁ……あっ、ん、んん……くぅ……ん、んあ、あああっ」",
        "byte_length": "0x3B"
    },
    {
        "text": "その締まりも河童にとっては極上の快楽にしかならず、より一層突き入れる腰の動きに力が入っていった。",
        "TL key": "その締まりも河童にとっては極上の快楽にしかならず、より一層突き入れる腰の動きに力が入っていった。",
        "byte_length": "0x61"
    },
    {
        "text": "「ひあっ、んんっ、あっ……んんーっ……」",
        "TL key": "「ひあっ、んんっ、あっ……んんーっ……」",
        "byte_length": "0x29"
    },
    {
        "text": "「うあぁ……あっ、やんっ、ひあ、あ……やめてぇ……奥を突かないでっ、苦しいのです……」",
        "TL key": "「うあぁ……あっ、やんっ、ひあ、あ……やめてぇ……奥を突かないでっ、苦しいのです……」",
        "byte_length": "0x57"
    },
    {
        "text": "みくるの言葉に河童は首を捻ると、挿入の角度を変えてきた。",
        "TL key": "みくるの言葉に河童は首を捻ると、挿入の角度を変えてきた。",
        "byte_length": "0x39"
    },
    {
        "text": "「ひゃああんっ、そこ、もっとダメですっ、あああ」",
        "TL key": "「ひゃああんっ、そこ、もっとダメですっ、あああ」",
        "byte_length": "0x31"
    },
    {
        "text": "角度を変えたことで腸壁越しに子宮を突かれたのだ。",
        "TL key": "角度を変えたことで腸壁越しに子宮を突かれたのだ。",
        "byte_length": "0x31"
    },
    {
        "text": "「あっ、やっ、そこはっ、いやあっ、んんっ、はぁぁん」",
        "TL key": "「あっ、やっ、そこはっ、いやあっ、んんっ、はぁぁん」",
        "byte_length": "0x35"
    },
    {
        "text": "みくるが喘ぐ声に僅かな艶が乗ってきた。",
        "TL key": "みくるが喘ぐ声に僅かな艶が乗ってきた。",
        "byte_length": "0x27"
    },
    {
        "text": "河童は心得たとばかりに子宮や膀胱を突いてくる。",
        "TL key": "河童は心得たとばかりに子宮や膀胱を突いてくる。",
        "byte_length": "0x2F"
    },
    {
        "text": "「ああっ、あっあっ、やっ、ダメっ、ダメなのですぅっ、ああん」",
        "TL key": "「ああっ、あっあっ、やっ、ダメっ、ダメなのですぅっ、ああん」",
        "byte_length": "0x3D"
    },
    {
        "text": "弱いところを突かれたみくるは、つま先立ってしまう。",
        "TL key": "弱いところを突かれたみくるは、つま先立ってしまう。",
        "byte_length": "0x33"
    },
    {
        "text": "河童はみくるの手を引き、ベストポジションに腰を据えさせる。",
        "TL key": "河童はみくるの手を引き、ベストポジションに腰を据えさせる。",
        "byte_length": "0x3B"
    },
    {
        "text": "「ひゃあんっ、深いっ、あっ、やっ……」",
        "TL key": "「ひゃあんっ、深いっ、あっ、やっ……」",
        "byte_length": "0x27"
    },
    {
        "text": "みくるを快楽から逃がすまいとして、直腸を掻き回してきた。",
        "TL key": "みくるを快楽から逃がすまいとして、直腸を掻き回してきた。",
        "byte_length": "0x39"
    },
    {
        "text": "（んあっ、やっ、いろんな所に当たってるっ、ふああ……）",
        "TL key": "（んあっ、やっ、いろんな所に当たってるっ、ふああ……）",
        "byte_length": "0x37"
    },
    {
        "text": "喘ぎ声が一際大きくなり、河童を喜ばせる。",
        "TL key": "喘ぎ声が一際大きくなり、河童を喜ばせる。",
        "byte_length": "0x29"
    },
    {
        "text": "「はぁっ、あん、ん、んあ、あ、ああっひゃう、ん、んはぁあああっ！」",
        "TL key": "「はぁっ、あん、ん、んあ、あ、ああっひゃう、ん、んはぁあああっ！」",
        "byte_length": "0x43"
    },
    {
        "text": "（お……お尻で……気持ち良くなるなんて……）",
        "TL key": "（お……お尻で……気持ち良くなるなんて……）",
        "byte_length": "0x2D"
    },
    {
        "text": "「ひゃんっ、変ですっ、あああっ、変な感じでなのすっ」",
        "TL key": "「ひゃんっ、変ですっ、あああっ、変な感じでなのすっ」",
        "byte_length": "0x35"
    },
    {
        "text": "みくるの反応に気を良くしたのか、抽送のピッチをあげてくる。",
        "TL key": "みくるの反応に気を良くしたのか、抽送のピッチをあげてくる。",
        "byte_length": "0x3B"
    },
    {
        "text": "ぬちゅっ、にちゅっ、くちゅっ……",
        "TL key": "ぬちゅっ、にちゅっ、くちゅっ……",
        "byte_length": "0x21"
    },
    {
        "text": "川のせせらぎ音に混じって、菊門から出る水音と、肉体がぶつかり合う音が重なる。",
        "TL key": "川のせせらぎ音に混じって、菊門から出る水音と、肉体がぶつかり合う音が重なる。",
        "byte_length": "0x4D"
    },
    {
        "text": "「あっ、あっ、やっ、激しいの、ダメですっ、んあぁ」",
        "TL key": "「あっ、あっ、やっ、激しいの、ダメですっ、んあぁ」",
        "byte_length": "0x33"
    },
    {
        "text": "尻奥を貫かれる毎にみくるの喘ぎ声が漏れる。",
        "TL key": "尻奥を貫かれる毎にみくるの喘ぎ声が漏れる。",
        "byte_length": "0x2B"
    },
    {
        "text": "「はあっ、息、苦しいっ、ふあぁっ、はあんっ、はぁん」",
        "TL key": "「はあっ、息、苦しいっ、ふあぁっ、はあんっ、はぁん」",
        "byte_length": "0x35"
    },
    {
        "text": "みくるの喘ぎ声は徐々に甘くなり、ますます河童を喜ばせる。",
        "TL key": "みくるの喘ぎ声は徐々に甘くなり、ますます河童を喜ばせる。",
        "byte_length": "0x39"
    },
    {
        "text": "ぱちゃっ、くちゅっ、ぱんっ、ぱんっ……",
        "TL key": "ぱちゃっ、くちゅっ、ぱんっ、ぱんっ……",
        "byte_length": "0x27"
    },
    {
        "text": "「いやあっ、エッチな音がしてるっ、やあぁ……」",
        "TL key": "「いやあっ、エッチな音がしてるっ、やあぁ……」",
        "byte_length": "0x2F"
    },
    {
        "text": "喘ぎ、叫ぶ毎に括約筋が勝手に締まり、それが河童を喜ばせた。",
        "TL key": "喘ぎ、叫ぶ毎に括約筋が勝手に締まり、それが河童を喜ばせた。",
        "byte_length": "0x3B"
    },
    {
        "text": "パンパンと尻肉に打ち付ける音が甲高く、早くなるにつれてみくるも快楽の坩堝へと引き込まれてゆく。",
        "TL key": "パンパンと尻肉に打ち付ける音が甲高く、早くなるにつれてみくるも快楽の坩堝へと引き込まれてゆく。",
        "byte_length": "0x5F"
    },
    {
        "text": "「んあぁっ、ごりごりしてるっ、ふあぁ……」",
        "TL key": "「んあぁっ、ごりごりしてるっ、ふあぁ……」",
        "byte_length": "0x2B"
    },
    {
        "text": "徐々に高まる快感からみくるの胸元が桜色に染まる。",
        "TL key": "徐々に高まる快感からみくるの胸元が桜色に染まる。",
        "byte_length": "0x31"
    },
    {
        "text": "「ああっ、んんっ、やあんっ、お尻っ、気持ちいい……」",
        "TL key": "「ああっ、んんっ、やあんっ、お尻っ、気持ちいい……」",
        "byte_length": "0x35"
    },
    {
        "text": "不快感が快感に変わったことでみくるは自ら腰を振って行為を受け入れようとする。",
        "TL key": "不快感が快感に変わったことでみくるは自ら腰を振って行為を受け入れようとする。",
        "byte_length": "0x4D"
    },
    {
        "text": "にちゅっ、にちゃっ……",
        "TL key": "にちゅっ、にちゃっ……",
        "byte_length": "0x17"
    },
    {
        "text": "裂け目に当たる河童の陰嚢は愛蜜に濡れて糸を引く。",
        "TL key": "裂け目に当たる河童の陰嚢は愛蜜に濡れて糸を引く。",
        "byte_length": "0x31"
    },
    {
        "text": "「やああっ、お腹の奥がじんじんするっ、ふあぁん」",
        "TL key": "「やああっ、お腹の奥がじんじんするっ、ふあぁん」",
        "byte_length": "0x31"
    },
    {
        "text": "最初は苦しくて嫌なだけだった行為が、今はとても気持ちよくなっていた。",
        "TL key": "最初は苦しくて嫌なだけだった行為が、今はとても気持ちよくなっていた。",
        "byte_length": "0x45"
    },
    {
        "text": "「いやあっ、立っていられないっ、あっやっ」",
        "TL key": "「いやあっ、立っていられないっ、あっやっ」",
        "byte_length": "0x2B"
    },
    {
        "text": "河童の腰使いが激しくなり、腰を打ち付けられたみくるの尻肉が紅く染まってゆく。",
        "TL key": "河童の腰使いが激しくなり、腰を打ち付けられたみくるの尻肉が紅く染まってゆく。",
        "byte_length": "0x4D"
    },
    {
        "text": "「あああ……もう立っていられないのです、ふあぁん」",
        "TL key": "「あああ……もう立っていられないのです、ふあぁん」",
        "byte_length": "0x33"
    },
    {
        "text": "みくるは快感から膝をガクガクと震わせる。",
        "TL key": "みくるは快感から膝をガクガクと震わせる。",
        "byte_length": "0x29"
    },
    {
        "text": "「許してくださいっ、ん、んあ……あっ、あぁああっ！」",
        "TL key": "「許してくださいっ、ん、んあ……あっ、あぁああっ！」",
        "byte_length": "0x35"
    },
    {
        "text": "河童は膝を曲げたみくるの両手をしっかりと掴み、立たせようと引き寄せる。",
        "TL key": "河童は膝を曲げたみくるの両手をしっかりと掴み、立たせようと引き寄せる。",
        "byte_length": "0x47"
    },
    {
        "text": "「いやああっ、そこ、ダメダメっ、我慢できないのですっ」",
        "TL key": "「いやああっ、そこ、ダメダメっ、我慢できないのですっ」",
        "byte_length": "0x37"
    },
    {
        "text": "挿入の角度が変わったことで、河童の亀頭は容赦なく子宮の裏側を突きまくってきた。",
        "TL key": "挿入の角度が変わったことで、河童の亀頭は容赦なく子宮の裏側を突きまくってきた。",
        "byte_length": "0x4F"
    },
    {
        "text": "「あっあっだめっ、あんっ、子宮壊れる、壊れるぅ……」",
        "TL key": "「あっあっだめっ、あんっ、子宮壊れる、壊れるぅ……」",
        "byte_length": "0x35"
    },
    {
        "text": "いやいやをするみくるに、河童は動きを強く、激しくしてゆく。",
        "TL key": "いやいやをするみくるに、河童は動きを強く、激しくしてゆく。",
        "byte_length": "0x3B"
    },
    {
        "text": "「んあっ、くぅんっ、ああっ、あふっ、あああぁぁ……」",
        "TL key": "「んあっ、くぅんっ、ああっ、あふっ、あああぁぁ……」",
        "byte_length": "0x35"
    },
    {
        "text": "（ああ……頭がぼんやりしてきたのです……）",
        "TL key": "（ああ……頭がぼんやりしてきたのです……）",
        "byte_length": "0x2B"
    },
    {
        "text": "快感に飲み込まれたみくるに、思考する力は残っていなかった。",
        "TL key": "快感に飲み込まれたみくるに、思考する力は残っていなかった。",
        "byte_length": "0x3B"
    },
    {
        "text": "ただ河童の行為に身を委ね、快楽を享受するばかりだ。",
        "TL key": "ただ河童の行為に身を委ね、快楽を享受するばかりだ。",
        "byte_length": "0x33"
    },
    {
        "text": "「ふああっ、お腹の奥が熱いのですっ、いやぁぁん」",
        "TL key": "「ふああっ、お腹の奥が熱いのですっ、いやぁぁん」",
        "byte_length": "0x31"
    },
    {
        "text": "直腸奥を突かれる悦びに歓喜の声をあげてしまう。",
        "TL key": "直腸奥を突かれる悦びに歓喜の声をあげてしまう。",
        "byte_length": "0x2F"
    },
    {
        "text": "「んんっ、はぁっ、やあっ、んんっ、ああっ、やっやっ……」",
        "TL key": "「んんっ、はぁっ、やあっ、んんっ、ああっ、やっやっ……」",
        "byte_length": "0x39"
    },
    {
        "text": "抽送はますます深く、早くなり河童の逸物が直腸内で膨らんだ。",
        "TL key": "抽送はますます深く、早くなり河童の逸物が直腸内で膨らんだ。",
        "byte_length": "0x3B"
    },
    {
        "text": "「やあっ、太いのっ、ああっ、ごりごりするぅ……」",
        "TL key": "「やあっ、太いのっ、ああっ、ごりごりするぅ……」",
        "byte_length": "0x31"
    },
    {
        "text": "みくるの頭の中に閃光が走り、視界が真っ白になってゆく。",
        "TL key": "みくるの頭の中に閃光が走り、視界が真っ白になってゆく。",
        "byte_length": "0x37"
    },
    {
        "text": "「んあっ、あ、あぁああっ！　もうっ、だめっ、おかしくなるっ、おかしくなるぅぅぅぅぅ！」",
        "TL key": "「んあっ、あ、あぁああっ！　もうっ、だめっ、おかしくなるっ、おかしくなるぅぅぅぅぅ！」",
        "byte_length": "0x57"
    },
    {
        "text": "「あん、あ、あぁっ！　もうダメっ、イクっ、イクイクイクぅぅぅぅぅぅぅ！」",
        "TL key": "「あん、あ、あぁっ！　もうダメっ、イクっ、イクイクイクぅぅぅぅぅぅぅ！」",
        "byte_length": "0x49"
    },
    {
        "text": "膝頭を震わせたみくるの直腸内で、河童の逸物が爆ぜた。",
        "TL key": "膝頭を震わせたみくるの直腸内で、河童の逸物が爆ぜた。",
        "byte_length": "0x35"
    },
    {
        "text": "「あああああぁぁっ！！！」",
        "TL key": "「あああああぁぁっ！！！」",
        "byte_length": "0x1B"
    },
    {
        "text": "どくどくと脈を打って射精する河童に、みくるも絶頂する。",
        "TL key": "どくどくと脈を打って射精する河童に、みくるも絶頂する。",
        "byte_length": "0x37"
    },
    {
        "text": "「んああぁっ！　ひぃっ！　ひああああぁぁぁぁぁ！」",
        "TL key": "「んああぁっ！　ひぃっ！　ひああああぁぁぁぁぁ！」",
        "byte_length": "0x33"
    },
    {
        "text": "「やぁぁんっ、お尻、熱いっ、熱ぅぅいっ」",
        "TL key": "「やぁぁんっ、お尻、熱いっ、熱ぅぅいっ」",
        "byte_length": "0x29"
    },
    {
        "text": "尻穴だけではなく膣穴まで激しく収縮し、腰が大きく震えていた。",
        "TL key": "尻穴だけではなく膣穴まで激しく収縮し、腰が大きく震えていた。",
        "byte_length": "0x3D"
    },
    {
        "text": "「はぅんっ、ミク、お尻でイッちゃぅぅ……」",
        "TL key": "「はぅんっ、ミク、お尻でイッちゃぅぅ……」",
        "byte_length": "0x2B"
    },
    {
        "text": "背を仰け反らせて絶頂するみくるを、河童は激しく突いてくる。",
        "TL key": "背を仰け反らせて絶頂するみくるを、河童は激しく突いてくる。",
        "byte_length": "0x3B"
    },
    {
        "text": "「やあっ、またイクっ、イクイクっ、ひゃぅぅん……」",
        "TL key": "「やあっ、またイクっ、イクイクっ、ひゃぅぅん……」",
        "byte_length": "0x33"
    },
    {
        "text": "後れ毛を逆立てて絶頂を繰り返すみくる。",
        "TL key": "後れ毛を逆立てて絶頂を繰り返すみくる。",
        "byte_length": "0x27"
    },
    {
        "text": "河童は射精してもなお、みくるの中へ抽送する。",
        "TL key": "河童は射精してもなお、みくるの中へ抽送する。",
        "byte_length": "0x2D"
    },
    {
        "text": "「あああっ、もうダメですっ、やっ、またイク……」",
        "TL key": "「あああっ、もうダメですっ、やっ、またイク……」",
        "byte_length": "0x31"
    },
    {
        "text": "「イクイクイクっ、ああっ、イックくうううう……」",
        "TL key": "「イクイクイクっ、ああっ、イックくうううう……」",
        "byte_length": "0x31"
    },
    {
        "text": "大きな絶頂を迎えたみくるは、そのまま脱力してしまった。",
        "TL key": "大きな絶頂を迎えたみくるは、そのまま脱力してしまった。",
        "byte_length": "0x37"
    },
    {
        "text": "「はあっ、はあっ、んくっ、はぁぁ……」",
        "TL key": "「はあっ、はあっ、んくっ、はぁぁ……」",
        "byte_length": "0x27"
    },
    {
        "text": "激しい絶頂の余韻に身を任せたみくるは、ぐったりとする。",
        "TL key": "激しい絶頂の余韻に身を任せたみくるは、ぐったりとする。",
        "byte_length": "0x37"
    },
    {
        "text": "「はぁっ、ふうっ、んんっ、はぁっ……」",
        "TL key": "「はぁっ、ふうっ、んんっ、はぁっ……」",
        "byte_length": "0x27"
    },
    {
        "text": "みくるは何度も深呼吸をする。",
        "TL key": "みくるは何度も深呼吸をする。",
        "byte_length": "0x1D"
    },
    {
        "text": "喘ぎすぎて酸欠に近い状態に陥ったのだ。",
        "TL key": "喘ぎすぎて酸欠に近い状態に陥ったのだ。",
        "byte_length": "0x27"
    },
    {
        "text": "「はぁっ……はっ、あ……う……」",
        "TL key": "「はぁっ……はっ、あ……う……」",
        "byte_length": "0x21"
    },
    {
        "text": "河童の責めに疲労{困憊/こんぱい}状態のみくるはゆっくりと瞼を閉じる。",
        "TL key": "河童の責めに疲労{困憊/こんぱい}状態のみくるはゆっくりと瞼を閉じる。",
        "byte_length": "0x44"
    },
    {
        "text": "「はぁ……、はぁ…………うぅ…………ん…………」",
        "TL key": "「はぁ……、はぁ…………うぅ…………ん…………」",
        "byte_length": "0x31"
    },
    {
        "text": "そして、すぐそばに流れている川のせせらぎを聴きながらみくるは意識を手放すのだった。",
        "TL key": "そして、すぐそばに流れている川のせせらぎを聴きながらみくるは意識を手放すのだった。",
        "byte_length": "0x53"
    }
]